Workbook

Sheet Assumptions
A1: Units | B1: 4
A2: Rent Per Unit | B2: 3500
A3: Months per year | B3: 12
A4: Vacancy Rate | B4: 0.1
A5: Rent Growth Rate | B5: 0.04
A6: Property Tax Rate | B6: 0.022
A7: Insurance Per Unit | B7: 4000
A8: Management % of EGI | B8: 0.08
A9: Reparis Per Unit | B9: 1000
A10: CapEx Per Unit | B10: 350
A11: Misc Expenses | B11: 2500
A12: Purchase Price | B12: 2000000
... A16: Exit Cap Rate | B16: 0.06
A18: Annual Operating Expenses (Detailed)
A19: Property Taxes | B19: =B12*B6 -> 44000
A20: Insurance | B20: =B7*B1 -> 16000
A21: Management
A22: Repairs | B22: =B9*B1 -> 4000
A23: CapEx | B23: =B10*B1 -> 1400
A24: Misc | B24: 3000
A26: Annual Debt Service (Detailed)
A27: Loan Amount | B27: =B12*(1-B13) -> 1400000
A28: Monthly Payment | B28: =PMT(B14/12, B15*12,-B27) -> 9239.3803
A29: Annual Debt Service | B29: =B28*12 -> 110872.56

Sheet CF (10 Year Model)
A1: Year | B1: GPR | C1: Vacancy Loss | D1: EGI | E1: OpEx | F1: NOI | G1: Debt Service | H1: CFBT | I1: Sale Proceeds | J1: Total CF
A2: 0 | H2: =J2 -> -600000 | J2: =Assumptions!B27-Assumptions!B12 -> -600000
A3: 1 | B3: =Assumptions!B1*Assumptions!B2*Assumptions!B3 -> 168000 | C3: =B3*Assumptions!B4 -> 16800 | D3: =B3-C3 -> 151200 | E3: =Assumptions!B19+Assumptions!B20+(D3*Assumptions!B8)+Assumptions!B22+Assumptions!B23+Assumptions!B24 -> 80496 | F3: =D3-E3 -> 70704 | G3: =Assumptions!B29 -> 110872.56 | H3: =F3-G3 -> -40168.564 | J3: =H3 -> -40168.564
A4: 2 | B4: =B3*(1+Assumptions!B5) -> 174720 | C4: =B4*Assumptions!B4 -> 17472 | D4: =B4-C4 -> 157248 | E4: =Assumptions!B19+Assumptions!B20+(D4*Assumptions!B8)+Assumptions!B22+Assumptions!B23+Assumptions!B24 -> 80979.84 | F4: =D4-E4 -> 76268.16 | G4: =Assumptions!B29 -> 110872.56 | H4: =F4-G4 -> -34604.404 | J4: =H4 -> -34604.404
A5: 3 | B5: =B4*(1+ Assumptions!B5) -> 181708.8 | C5: =B5*Assumptions!B4 -> 18170.88 | D5: =B5-C5 -> 163537.92 | E5: =Assumptions!B19+Assumptions!B20+(D5*Assumptions!B8)+Assumptions!B22+Assumptions!B23+Assumptions!B24 -> 81483.034 | F5: =D5-E5 -> 82054.886 | G5: =Assumptions!B29 -> 110872.56 | H5: =F5-G5 -> -28817.678 | J5: =H5 -> -28817.678
A6: 4 | B6: =B5*(1+ Assumptions!B5) -> 188977.15 | C6: =B6*Assumptions!B4 -> 18897.715 | D6: =B6-C6 -> 170079.44 | E6: =Assumptions!B19+Assumptions!B20+(D6*Assumptions!B8)+Assumptions!B22+Assumptions!B23+Assumptions!B24 -> 82006.355 | F6: =D6-E6 -> 88073.082 | G6: =Assumptions!B29 -> 110872.56 | H6: =F6-G6 -> -22799.482 | J6: =H6 -> -22799.482
A7: 5 | B7: =B6*(1+ Assumptions!B5) -> 196536.24 | C7: =B7*Assumptions!B4 -> 19653.624 | D7: =B7-C7 -> 176882.61 | E7: =Assumptions!B19+Assumptions!B20+(D7*Assumptions!B8)+Assumptions!B22+Assumptions!B23+Assumptions!B24 -> 82550.609 | F7: =D7-E7 -> 94332.005 | G7: =Assumptions!B29 -> 110872.56 | H7: =F7-G7 -> -16540.559 | J7: =H7 -> -16540.559
A8: 6 | B8: =B7*(1+ Assumptions!B5) -> 204397.69 | C8: =B8*Assumptions!B4 -> 20439.769 | D8: =B8-C8 -> 183957.92 | E8: =Assumptions!B19+Assumptions!B20+(D8*Assumptions!B8)+Assumptions!B22+Assumptions!B23+Assumptions!B24 -> 83116.634 | F8: =D8-E8 -> 100841.29 | G8: =Assumptions!B29 -> 110872.56 | H8: =F8-G8 -> -10031.279 | J8: =H8 -> -10031.279
A9: 7 | B9: =B8*(1+ Assumptions!B5) -> 212573.6 | C9: =B9*Assumptions!B4 -> 21257.36 | D9: =B9-C9 -> 191316.24 | E9: =Assumptions!B19+Assumptions!B20+(D9*Assumptions!B8)+Assumptions!B22+Assumptions!B23+Assumptions!B24 -> 83705.299 | F9: =D9-E9 -> 107610.94 | G9: =Assumptions!B29 -> 110872.56 | H9: =F9-G9 -> -3261.6274 | J9: =H9 -> -3261.6274
A10: 8 | B10: =B9*(1+ Assumptions!B5) -> 221076.54 | C10: =B10*Assumptions!B4 -> 22107.654 | D10: =B10-C10 -> 198968.89 | E10: =Assumptions!B19+Assumptions!B20+(D10*Assumptions!B8)+Assumptions!B22+Assumptions!B23+Assumptions!B24 -> 84317.511 | F10: =D10-E10 -> 114651.37 | G10: =Assumptions!B29 -> 110872.56 | H10: =F10-G10 -> 3778.81 | J10: =H10 -> 3778.81
A11: 9 | B11: =B10*(1+ Assumptions!B5) -> 229919.6 | C11: =B11*Assumptions!B4 -> 22991.96 | D11: =B11-C11 -> 206927.64 | E11: =Assumptions!B19+Assumptions!B20+(D11*Assumptions!B8)+Assumptions!B22+Assumptions!B23+Assumptions!B24 -> 84954.211 | F11: =D11-E11 -> 121973.43 | G11: =Assumptions!B29 -> 110872.56 | H11: =F11-G11 -> 11100.865 | J11: =H11 -> 11100.865
A12: 10 | B12: =B11*(1+ Assumptions!B5) -> 239116.38 | C12: =B12*Assumptions!B4 -> 23911.638 | D12: =B12-C12 -> 215204.75 | E12: =Assumptions!B19+Assumptions!B20+(D12*Assumptions!B8)+Assumptions!B22+Assumptions!B23+Assumptions!B24 -> 85616.38 | F12: =D12-E12 -> 129588.37 | G12: =Assumptions!B29 -> 110872.56 | H12: =F12-G12 -> 18715.802 | I12: =F12/Assumptions!B16 -> 2159806.1 | J12: =H12+I12 -> 2178521.9
A21: IRR | B21: =IRR(J2:J12) -> 0.11877558
A22: PV | B22: =J12/(1+0.1)^10 -> 839914.5
A23: NPV | B23: =NPV(0.1, J4:J12) + (Assumptions!B12*Assumptions!B13) -> 1439252.2
A24: Equity Multiple | B24: =SUM(J3:J12)/(Assumptions!B12* Assumptions!B13) -> 3.3952966

Sheet Model Summary
A1: Key Assumptions | F1: Investment Results
A2: Purchase Price | B2: =Assumptions!B12 -> 2000000 | F2: Year 1 NOI | G2: ='CF (10 Year Model)'!F3 -> 70704
A3: Rent/ Unit | B3: =Assumptions!B2 -> 3500 | F3: Year 10 NOI | G3: ='CF (10 Year Model)'!F12 -> 129588.37
A4: Rent Growth | B4: =Assumptions!B5 -> 0.04 | F4: IRR | G4: ='CF (10 Year Model)'!B21 -> 0.11877558
A5: Vacancy Rate | B5: =Assumptions!B4 -> 0.1 | F5: NPV | G5: ='CF (10 Year Model)'!B23 -> 1439252.2
A6: Loan Interest Rate | B6: =Assumptions!B14 -> 0.05 | F6: Equity Multiple | G6: ='CF (10 Year Model)'!B24 -> 3.3952966
A7: Loan Term (Years) | B7: =Assumptions!B15 -> 20 | F7: Avg Annual CFBT | G7: =AVERAGE('CF (10 Year Model)'!H2:H12) -> -65693.465
A8: Exit Cap Rate | B8: =Assumptions!B16 -> 0.06
A25: Ad Hoc Analysis
A26: A $200/month increase in rent per unit improves IRR by ~1.80% and turns cash flow breakeven by Year 7.
A27: This leveraged investment deal creates significant value relative to the equity invested
